cml/__init__.py
cml/__main__.py
cml/cml.py
chanml_client-0.1.1.dist-info/entry_points.txt
chanml_client-0.1.1.dist-info/WHEEL
chanml_client-0.1.1.dist-info/METADATA
chanml_client-0.1.1.dist-info/RECORD
